fastapi_tag/__init__.py
fastapi_tag/api.py
fastapi_tag/application.py
fastapi_tag/metadata.py
fastapi_tag/model.py
fastapi_tag/py.typed
fastapi_tag/routers.py
fastapi_tag/type.py
fastapi_tag-1.0.0.dist-info/METADATA
fastapi_tag-1.0.0.dist-info/WHEEL
fastapi_tag-1.0.0.dist-info/licenses/LICENSE
fastapi_tag-1.0.0.dist-info/RECORD
